tripper/__init__.py
tripper/interface.py
tripper/triplestore.py
tripper/backends/__init__.py
tripper/backends/ontopy.py
tripper/backends/rdflib.py
tripperpy-0.1.0.dist-info/LICENSE
tripperpy-0.1.0.dist-info/WHEEL
tripperpy-0.1.0.dist-info/METADATA
tripperpy-0.1.0.dist-info/RECORD
