Metadata-Version: 2.1
Name: tripperpy
Version: 0.1.0
Summary: A triplestore wrapper for Python.
Keywords: triplestore,ontology,RDF
Author-email: Jesper Friis <jesper.friis@sintef.no>, Casper Welzel Andersen <casper.w.andersen@sintef.no>, "Thomas F. Hagelien" <thomas.f.hagelien@sintef.no>
Requires-Python: ~=3.7
Classifier: Development Status :: 2 - Pre-Alpha
Classifier: License :: OSI Approved :: MIT License
Classifier: Programming Language :: Python :: 3
Classifier: Programming Language :: Python :: 3.7
Classifier: Programming Language :: Python :: 3.8
Classifier: Programming Language :: Python :: 3.9
Classifier: Programming Language :: Python :: 3.10
Classifier: Environment :: Plugins
Classifier: Natural Language :: English
Classifier: Operating System :: OS Independent
Requires-Dist: EMMOntoPy ~=0.4
Requires-Dist: rdflib ~=6.2
Requires-Dist: typing-extensions ~=4.4 ; python_version<'3.8'
Requires-Dist: mike ~=1.1 ; extra == "dev"
Requires-Dist: mkdocs ~=1.3 ; extra == "dev"
Requires-Dist: mkdocs-awesome-pages-plugin ~=2.8 ; extra == "dev"
Requires-Dist: mkdocs-material ~=8.5 ; extra == "dev"
Requires-Dist: mkdocstrings[python-legacy] ~=0.19.0 ; extra == "dev"
Requires-Dist: pre-commit ~=2.20 ; extra == "dev"
Requires-Dist: pylint ~=2.15 ; extra == "dev"
Requires-Dist: pytest ~=7.1 ; extra == "dev"
Requires-Dist: pytest-cov ~=4.0 ; extra == "dev"
Requires-Dist: mike ~=1.1 ; extra == "docs"
Requires-Dist: mkdocs ~=1.3 ; extra == "docs"
Requires-Dist: mkdocs-awesome-pages-plugin ~=2.8 ; extra == "docs"
Requires-Dist: mkdocs-material ~=8.5 ; extra == "docs"
Requires-Dist: mkdocstrings[python-legacy] ~=0.19.0 ; extra == "docs"
Requires-Dist: pre-commit ~=2.20 ; extra == "pre-commit"
Requires-Dist: pylint ~=2.15 ; extra == "pre-commit"
Requires-Dist: pytest ~=7.1 ; extra == "testing"
Requires-Dist: pytest-cov ~=4.0 ; extra == "testing"
Project-URL: Changelog, https://github.com/EMMC-ASBL/tripper/blob/main/CHANGELOG.md
Project-URL: Documentation, https://EMMC-ASBL.github.io/tripper
Project-URL: Home, https://github.com/EMMC-ASBL/tripper
Project-URL: Issue Tracker, https://github.com/EMMC-ASBL/tripper/issues
Project-URL: Package, https://pypi.org/project/tripper
Project-URL: Source, https://github.com/EMMC-ASBL/tripper
Provides-Extra: dev
Provides-Extra: docs
Provides-Extra: pre-commit
Provides-Extra: testing
